sisc/__init__.py
sisc/alignment/BaseFileAligner.py
sisc/alignment/JsonAligner.py
sisc/alignment/TeiXmlAligner.py
sisc/alignment/TxtAligner.py
sisc/alignment/__init__.py
sisc/cli/AlignException.py
sisc/cli/NotSupportedException.py
sisc/cli/SisCCLI.py
sisc/cli/__init__.py
sisc/core/SisC.py
sisc/core/__init__.py
sisc/eval/Evaluation.py
sisc/eval/__init__.py
sisc/fingerprint/BaseFingerprinter.py
sisc/fingerprint/Note.py
sisc/fingerprint/TeiXmlFingerprinter.py
sisc/fingerprint/TextFingerprinter.py
sisc/fingerprint/__init__.py
sisc/mask/BaseMasker.py
sisc/mask/ContextMasker.py
sisc/mask/UniformMasker.py
sisc/mask/__init__.py
sisc/pdf/BasePdfExtractor.py
sisc/pdf/Pdf.py
sisc/pdf/TesseractException.py
sisc/pdf/TesseractExtractor.py
sisc/pdf/__init__.py
sisc/runexp/RunExp.py
sisc/runexp/__init__.py
sisc/util/Constants.py
sisc/util/Defaults.py
sisc/util/__init__.py
sisc-0.1.0.dist-info/licenses/LICENSE
sisc-0.1.0.dist-info/METADATA
sisc-0.1.0.dist-info/WHEEL
sisc-0.1.0.dist-info/entry_points.txt
sisc-0.1.0.dist-info/top_level.txt
sisc-0.1.0.dist-info/RECORD
