Metadata-Version: 2.4
Name: SisC
Version: 0.1.0
Summary: SisC is a tool to automatically separate  annotations from the underlying text. SisC uses a fingerprint, that is, a masked version  of the text to merge stand-off annotations with another version of the original text, for example, extracted from a PDF file. The fingerprint cannot be used on its own to recreate (meaningful parts of) the original text and can therefore be shared.
Author-email: Frederik Arnold <frederik.arnold@hu-berlin.de>
License:                                  Apache License
Project-URL: Homepage, https://hu.berlin/sisc
Keywords: sharing,annotation,openaccess
Classifier: Programming Language :: Python :: 3
Classifier: License :: OSI Approved :: Apache Software License
Classifier: Operating System :: OS Independent
Requires-Python: >=3.11
License-File: LICENSE
Requires-Dist: biopython>=1.84
Requires-Dist: pdf2image>=1.17.0
Requires-Dist: rapidfuzz>=3.10.0
Requires-Dist: lxml>=6.0.0
Dynamic: license-file
